README.txt
setup.py
BaleVK/__init__.py
BaleVK/console.py
BaleVK/fileio.py
BaleVK/formattingText.py
BaleVK/main.py
BaleVK/network.py
BaleVK/req.py
BaleVK/setup.py
BaleVK/updater.py
BaleVK.egg-info/PKG-INFO
BaleVK.egg-info/SOURCES.txt
BaleVK.egg-info/dependency_links.txt
BaleVK.egg-info/requires.txt
BaleVK.egg-info/top_level.txt